README.md
setup.py
odroute/__init__.py
odroute/cli.py
odroute/config.py
odroute/exceptions.py
odroute/frame.py
odroute/input.py
odroute/output.py
odroute/router.py
odroute/utils.py
odroute.egg-info/PKG-INFO
odroute.egg-info/SOURCES.txt
odroute.egg-info/dependency_links.txt
odroute.egg-info/entry_points.txt
odroute.egg-info/requires.txt
odroute.egg-info/top_level.txt
odroute/control/__init__.py
odroute/control/executor.py
odroute/control/rcserver.py
odroute/edi/__init__.py
odroute/edi/afpacket.py
odroute/edi/crc16.py
odroute/edi/decoder.py
odroute/edi/encoder.py