Metadata-Version: 1.0
Name: odroute
Version: 0.2.0
Summary: A tool to route streams from ODR-AudioEnc
Home-page: https://github.com/digris/odr-stream-router
Author: Jonas Ohrstrom
Author-email: ohrstrom@gmail.com
License: UNKNOWN
Platform: UNKNOWN
